lektor_pythonmarkdown.py
lektor_pythonmarkdown-1.2.dist-info/METADATA
lektor_pythonmarkdown-1.2.dist-info/RECORD
lektor_pythonmarkdown-1.2.dist-info/WHEEL
lektor_pythonmarkdown-1.2.dist-info/entry_points.txt
lektor_pythonmarkdown-1.2.dist-info/top_level.txt
