Metadata-Version: 2.1
Name: lektor-pythonmarkdown
Version: 1.2
Summary: Add pythonmarkdownn field type to Lektor to make use of python-markdown as a renderer.
Home-page: https://github.com/ikus060/lektor-python-markdown
Author: Patrik Dufresne Service Logiciel inc.
Author-email: info@patrikdufresne.com
License: MIT
Keywords: Lektor plugin static-site blog Python-Markdown
Platform: UNKNOWN
Classifier: Environment :: Plugins
Classifier: Environment :: Web Environment
Classifier: Framework :: Lektor
Classifier: Intended Audience :: Developers
Classifier: License :: OSI Approved :: MIT License
Requires-Dist: markdown
